{
  "title": "Отслойка и разрывы сетчатки",
  "url": "https://diseases.medelement.com/disease/%D0%BE%D1%82%D1%81%D0%BB%D0%BE%D0%B9%D0%BA%D0%B0-%D0%B8-%D1%80%D0%B0%D0%B7%D1%80%D1%8B%D0%B2%D1%8B-%D1%81%D0%B5%D1%82%D1%87%D0%B0%D1%82%D0%BA%D0%B8-2019/16482",
  "scraped_at": "2026-04-05T02:43:33.222722+00:00",
  "sections": {
    "definition": "Одобрен\nОбъединенной комиссией по качеству медицинских услуг\nМинистерства здравоохранения Республики Казахстан\nот «19» ноября 2019 года\nПротокол №77\nРегматогенная отслойка сетчатки – тяжелое заболевание, характеризующееся скоплением субретинальной жидкости через разрыв сетчатки между нейросенсорными слоями и подлежащим пигментным эпителием [1].\nРетиношизис и ретинальные кисты: Ретиношизис – это расслоение нейросенсорной сетчатки на внутрений и наружный листи, с повреждением нейронов и полной утратой поля зрения в области поражения [2].\nРетинальные разрывы без отслойки сетчатки - это сквозные дефекты в нейросенсорной сетчатке, которые различаются по патогенезу, конфигурации и локализации [3].\nТракционная отслойка сетчатки – происходит при натяжении (тракции), которое испытывает сетчатка со стороны стекловидного тела из-за образования в результате фибринозных тяжей или новообразованных сосудов, которые врастают в стекловидное тело [1].\nДругие формы отслойки сетчатки: Витреомакулярный тракционный синдром – хроническое состояние, связанное c неполной задней отслойкой стекловидного тела и преретинальной пролиферацией, которые вызывают тракционную деформацию макулы, механическое натяжение и повреждение макулярной сетчатки [4 - 6].\nВВОДНАЯ ЧАСТЬ\nНазвание протокола: ОТСЛОЙКА И РАЗРЫВЫ СЕТЧАТКИ",
    "classification": "Код Название\nH33.0 Отслойка сетчатки с разрывом сетчатки\nH33.1 Ретиношизис и ретинальные кисты\nH33.3 Ретинальные разрывы без отслойки сетчатки\nH33.4 Тракционная отслойка сетчатки\nH33.5 Другие формы отслойки сетчатки\nH43.8 Витреомакулярный тракционный синдром\nДата разработки/пересмотра протокола: 2015 год (пересмотр 2019 г.)\nСокращения, используемые в протоколе:\nАЛТ – аланинтрансфераза\nАСТ – аспартаттрансфераза\nБХ – биохимический анализ\nВГД – внутриглазное давление\nВИЧ – вирус иммуннодефицита человека\nВМТС – Витреомакулярный тракционный синдром\nОАК – общий анализ крови\nОАМ – общий анализ мочи\nОС – отслойка сетчатки\nПВР – пролиферативная витреоретинопатия\nПЗ – поле зрения\nПЗР – передне-задний размер глазного яблока.\nУД – уровень доказательности\nУЗИ – ультразвуковое исследование\nЭКГ – электрокардиограмма\nЭРГ – электроретинография\nЭФИ – электрофизиологическое исследование\nПользователи протокола: врачи общей практики, врачи скорой помощи, фельдшеры, офтальмологи.\nКатегория пациентов: взрослые.\nШкала уровня доказательности:\nОценка на степень доказательности приводимых рекомендаций [1].\nУровень\nдоказательности Тип доказательности\nІ Доказательства получены в результате мета-анализа большого числа хорошо спланированных рандомизированных исследований.\nРандомизированные исследования с низким уровнем ложнопозитивных и ложнонегативных ошибок.\nІІ Доказательства основаны на результатах не менее одного хорошо спланированного рандомизированного исследования. Рандомизированные исследования с высоким уровнем ложнопозитивных и ложнонегативных ошибок.\nІІІ Доказательства основаны на результатах хорошо спланированных нерандомизированных исследований. Контролируемые исследования с одной группой больных, исследования с группой исторического контроля и т.д.\nІV Доказательства получены в результате нерандомизированных исследований. Непрямые сравнительные, описательно корелляционные исследования и исследования клинических случаев.\nV Доказательства основаны на клинических случаях и примерах\nСтепень Градация\nА Доказательство І уровня или устойчивые многочисленные данные ІІ. ІІІ или ІV уровня доказательности\nВ Доказательства ІІ. ІІІ или ІV уровня, считающиеся в целом устойчивыми данными\nС Доказательства ІІ. ІІІ или ІV уровня, но данные в целом неустойчивые\nD Слабые или несистематические эмпирические доказательства.\nКлассификация\nКлиническая классификация\nКлассификация отслойка сетчатки по Краснову М.М. [7]:\nпо механизму:\nрегматогенная (с дырчатым или клапанным разрывом сетчатки, идиопатическая);\nтракционная (травма, СД, гемофтальм);\nсмешанная (тракционно-перфоративная, перфоративно-тракционная);\nэкссудативная.\nпо виду:\nсвежая (до 1 месяца);\nнесвежая (от 1 до 3 месяцев);\nстарая (от 3 месяцев и более).\nпо распространенности:\nлокальная (занимает 1 квадрант глазного дна);\nраспространенная (занимает до 2 квадрантов глазного дна);\nсубтотальная (занимает 3 квадранта глазного дна);\nтотальная (занимает всю площадь глазного дна).\nпо высоте:\nплоская;\nвысокая;\nпузыревидная.\nпо ригидности:\nподвижная;\nполуподвижная;\nригидная.\nКлассификация отслоек сетчатки по категории тяжести:\nI категория: cетчатка полностью мобильна, расправляемость хорошая, тракционный компонент со стороны стекловидного тела выражено слабо. После 3-4 дней постельного режима сетчатка прилежит в области разрыва к сосудистой оболочке. Фиксированные складки сетчатки и шварты в стекловидном теле отсутствуют.\nII категория: характеризуется тракцией со стороны стекловидного тела, после 3-4 дней постельного режима сетчатка частично (прилежит) расправляется, но полностью на месте разрыва не прилегает. Отмечаются шварты стекловидного тела, соединенные с клапаном разрыва, а также отслойка его стекловидной пластинки. Фиксированные складки сетчатки отсутствуют.\nIII категория: имеются выраженные тракционные изменения со стороны стекловидного тела. Нет тенденции к расправлению сетчатки даже после длительного постельного режима. Грубые фиксированные складки малоподвижны при движении глаза.\nКлассификация отслоек сетчатки с ПВР [1]:\nСтадия ПВР А. – стекловидное тело мутное, с пигментными глыбками. Пигментные глыбки на поверхности отслоенной сетчатки и в нижних отделах витреальной полости.\nСтадия ПВР В. – сморщивание поверхности отслоенной сетчатки, уменьшение ее подвижности, ретинальные сосуды извиты, край разрыва сетчатки завернут, стекловидное тело становится малоподвижным.\nСтадия ПВР С posterior – кзади от экватора формируются фокальные, диффузные фиксированные складки сетчатки, наличие субретинальных тяжей.\nСтадия ПВР Canterior – кпереди от экватора формируются фиксированные складки сетчатки, переднее смещение периферической сетчатки, плотное, тяжистое стекловидное тело.\nКлассификация ретиношизиса и ретинальные кисты по Астахову Ю.С., Луковской Н.Г. [2]:\nПо локализации разрыва в сетчатке:\nво внутреннем листке;\nв наружном листке;\nв обоих листках;\nбез разрывов.\nПо течению:\nстационарное с рубцеванием сетчатки;\nпрогрессирующее без демаркации с неровными границами;\nосложненное:\n- кровоизлияние в стекловидное тело;\n- кровоизлияние в полость кисты;\n- с переходом в отслойку сетчатки.\nПо виду:\nпервичный;\nвторичный;\nПо этиопатогенезу:\nнаследственный:\n- юношеский, сцепленный с Х-хромосомой;\n- при синдроме Вагнера;\n- при синдроме Гольдмана-Фавра.\nприобретенный:\nДегенеративный (сенильный):\n- из типичной кистозной периферической дегенерации;\n- из ретикулярной кистозной периферической дегенерации.\nМиопический:\n- из типичной кистозной периферической дегенерации;\n- из ретикулярной кистозной периферической дегенерации\n· после травмы\n· после тромбоза центральной вены сетчатки\n· после операции по поводу отслойки сетчатки\n· при диабете\n· при увеите\nПо локализации:\nцентральная;\nпериферическая;\nкомбинированная.\nПо форме:\nплоская;\nбуллезная.\nПо стороне поражения:\nодносторонний;\nдвусторонний.\nКлассификация ретинальных разрывов без отслойки сетчатки [3]:\nПо патогенезу:\nклапанные разрыв возникают при динамичекой витреоретинальной тракции. Наиболее часто встречается в верхнем квадранте (чаще височном).\nдырчатые разрывы возникают как следствие хронической атрофии сетчатки и бывают овальными и круглыми.\nПо конфигурации\nU-разрывы, клапанные или подковообразные разрывы, вершина которой тянется в стекловидное тело, а основание (расположенно ближе кпереди) остается прикрепленным к остальной сетчатке.\nНеполный  U- образный или L- образный разрыв.\nРазрыв с крышечкой, когда участок сетчатки полностью оторван отслоенным стекловидным телом.\nОтрыв (диализ) – это циркулярный разрыв вдоль зубчатой линии с прикрепленным по задней поверхности разрыва стекловидным телом.\nГигантские разрывы, распространяющие более чем на 90° окружности глазного яблока. Это вариант U –разрыва с прикреплением стекловидного тела по переднему краю разрыва.\nКлассификация витреомакулярного тракционного  синдрома[4-6].\nВиды Описание по OКT картине",
    "symptoms": "Симптомы Соответствует стадии макулярного отверстия:\nВитреомакулярная адгезия По крайней мере должен присуствовать один из следующих изменений на ОКТ картине:\n(I) Частичное отслоение стекловидного тела, указывающий на подъем кортикального слоя стекловидного тела над поверхностью сетчатки в перифовеалярной области.\n(II) Постоянное прикрепление стекловидного тела к макуле в пределах 3 мм в радиус от центра фовеа.\n(III) острый угол между задним гиалоидом и внутренней поверхностью сетчатки\n(IV) отсутствие изменений фовеального контура или морфологии сетчатки нет нет 0 стадия\nВитреомакулярная тракция По крайней мере должен присуствовать один из следующих изменений на ОКТ картине:\n(I) Частичное отслоение стекловидного тела, указывающий на подъем кортикального слоя стекловидного тела над поверхностью сетчатки в перифовеалярной области.\n(II) Постоянное прикрепление стекловидного тела к макуле в пределах 3 мм в радиус от центра фовеа.\n(III) острый угол между задним гиалоидом и внутренней поверхность сетчатки.\n(IV) отсутствие изменений фовеального контура или морфологии сетчатки (искривление фовеальной поверхности, интраретинальные структурные изменения как формирование псевдокисты, подъем фовеа от ПЭ, или комбинация любого из этих трех признаков).\n(v) Отсутствие нарушение непрерывности по всей толщине сетчатки   Фовеалярная псевдокиста, утолщение макулы, увеличение проницаемости капилляров сетчатки, макулярный шизис, кистозный макулярный отек,\nотслоение сетчатки Снижение или искажение  зрения  1 Стадия (надвигающийся макулярный разрыв) 2 стадия (витриомакулярная тракция с полным малым и средним макулярным разрывом) или\n3 стадия\n(витриомакулярная тракция с полным средним и большим макулярным разрывом)\nВиды OКT- классификация\nВитреомакулярная адгезия (I) Фокальная: ширина крепления ≤1500 мкм\n(II) Широкая: ширина крепления> 1500 мкм\n(I) Одновременная: связанный с другими изменениями в макулярной зоне (например, возрастная макулярная дегенерация, окклюзия центральной вены сетчатки, диабетический макулярный отек)\n(II) Изолированная: не связан с другими нарушениями макулярной зоны\nВитреомулярная тракция\nФокальная: ширина крепления ≤1500 мкм\n(II) Широкая: ширина крепления> 1500 мкм\n(I) Одновременная: связанный с другими изменениями в макулярной зоне (например, возрастная макулярная дегенерация, окклюзия центральной вены сетчатки, диабетический макулярный отек)\n(II) Изолированная: не связан с другими нарушениями макулярной зоны",
    "diagnostics": "МЕТОДЫ, ПОДХОДЫ И ПРОЦЕДУРЫ ДИАГНОСТИКИ\nДиагностические критерии [1,9 - 11]\nЖалобы:\nснижение остроты зрения;\nпоявление дефекта в периферическом поле зрения в виде темной завесы;\nискажение зрения.\nАнамнез:\nанте/постнатальный анамнез;\nсведения о сопутствующих и ранее перенесенных заболеваниях (включая аллергоанамнез);\nтравмы органа зрения.\nФизикальное обследование: нет.\nЛабораторные исследования: нет.\nИнструментальные исследования:\nопределение остроты зрения без/с очковой коррекцией – отсутствие/снижение остроты зрения;\nизмерение внутриглазного давления – повышение/снижение ВГД;\nВ-скан глаз (эхобиометрия): наличие ОС, ее высота, распространенность и конфигурация;\nА-скан глаз (эхобиометрия): патологические эхосигналы, наличие/отсутствие увеличения ПЗР;\nэлектрофизиологическое исследование зрительного нерва и сетчатки ‒ снижение проводимости зрительного нерва, снижение активности наружных слоев сетчатки;\nисследование полей зрения ‒ участки выпадения, соответствующие противоположенной локализации ОС.\nоптическая когерентная томография – наличие трации в макулярной зоны, эпиретниальная мембрана, макулярный разрыв.\nПоказания для консультации специалистов:\nконсультация невропатолога при наличии неврологической патологии;\nконсультация ЛОР врача для исключения острой инфекции;\nконсультация стоматолога для исключения острой инфекции;\nконсультация терапевта для исключения противопоказаний со стороны общего состояния.\nДифференциальный диагноз\nДифференциальная диагностика первичной отслойки сетчатки cо вторичной отслойкой сетчатки и отслойки сосудистой оболочки\nДиагноз Обоснование для дифференциальной диагностики Обследования Критерии исключения диагноза\nВторичная отслойка сетчатки\nНаличие проминенции сетчатки вследствие наличия патологического образования позади нее; преимущественно односторонний характер;\nчасто боковое смещение глазного яблока;\nнарушение репозиции глазного яблока при надавливании на глаз через сомкнутые веки;\nизменение рефракции вследствие изменения длины аксиальной оси глазного яблока и радиуса кривизны роговицы;\nв развитии процесса играют роль травма, гриппозная инфекция, воспалительные заболевания в придаточных пазухах носа;\nкартина хронического неспецифического воспаления, боли в орбите, отек век, хемоз, ограничение движения глазного яблока, диплопия, нередко повышение внутриглазного давления, экзофтальм;\nчасто картина застойного диска зрительного нерва при вовлечении заднего отдела орбиты.\nВизометрия: безболезненное или резкое снижение зрения (при захвате маклярной зоны)\nПериметрия: Выпадение в поле зрения возникает на стороне, противоположной расположению отслойки. «пелена» или «шторка» перед глазом\nОфтальмоскопия: отслойка сетчатки с соединительнотканными тяжами (шварт) или преретинальными мембранами, скоплениями экссудата, растяжением ее растущей опухолью или новообразованными сосудами, гематомой.\nУЗИ: отслойка сетчатки, цилиохориоидальная отслойка, кровоизлияние в стекловидное тело, хориоидальная меланома и шварты 1.Наличие разрыва сетчатки, и тракции со стороны стекловидного тела.\n2.отсутствие различных заболеваний и патологических состояний глаза\nОтслойка сосудистой оболочки\nвстречается как осложнение при хирургии глаукомы;\nотличия при офтальмоскопии: отсутствие разрывов сетчатки, отсутствие пространства и жидкости между сетчаткой и сосудистой\nоболочкой, отслоенного пузыря цвет темно – серый. Визометрия: снижение зрения\nПериметрия: относительная скатома.\nОфтальмоскопия: очаг шаровидной формы и занимает один или два квадранта, обычно кпереди от экватора. Она легко просвечивается, цвет ее светлый, проходящие по ней сосуды ярко-розового цвета.  1.Наличие разрыва сетчатки, и тракции со стороны стекловидного тела.\n2. наличие абсолютной скотомы",
    "treatment": "ТАКТИКА ЛЕЧЕНИЯ НА АМБУЛАТОРНОМ УРОВНЕ: нет.\nЛечение (стационар)\nТАКТИКА ЛЕЧЕНИЯ НА СТАЦИОНАРНОМ УРОВНЕ\nКарта наблюдения пациента, маршрутизация пациента (схемы):\nЦели лечения:\nанатомическое прилегание сетчатки;\nустранение тракции;\nповышение зрительных функций.\nТактика лечения: лечение только хирургическое. До операции назначаются местно мидриатики, противовоспалительные и антибактериальные препараты. Метод хирургического вмешательства определяется хирургом во время осмотра. Во время операции также применяются местные антибактериальные, противовоспалительные препараты и анестетики в виде капель и ретробульбарных инъекций. В послеоперационном периоде назначаются местно антибактериальные, противовоспалительные препараты. При выписке пациенту даются подробные рекомендации с применением глазных капель самостоятельно.\nНемедикаментозное лечение:\n·режим I, II;\n·стол №15.\nМедикаментозное лечение:\nФармакотерапевтическая группа Международное непатентованное наименование ЛС Способ применения Уровень доказательности\nМидриатики короткого и длительного действия(применяется 1/2 из указанных препаратов):\nтропикамид\nфенилэфрина гидрохлорид +\nТропикамид\nатропин\nИнстиляции в конъюнктивальную полость (УД – С) [12];\n(УД – В) [12];\n(УД – С) [12].\nАнтибактериальные глазные капли(применяется 1 из указанных препаратов) тобрамицин\nлевофлоксацин\nципрофлоксацин\nмоксифлоксацин В конъюнктивальный мешок\n(УД – С) [12];\n(УД – С) [12];\n(УД – С)[12];\n(УД – С)\nПротивовоспалительные глазные капли (применяется 1 из указанных препаратов) дексаметазон\nнепафенак\nдиклофенак натрия Инстилляции в конъюнктивальную полость\nсуспензия по 1 капле 3 раза в день (УД – С)[12];\n(УД – С) [12];\n(УД – С) [12].\nКомбинированные препараты (применяется 1 из указанных препаратов) тобрамицин + дексаметазон\nгентамицин + дексаметазон в\nмоксифлоксацин+дексаметазон в конъюнктивальный мешок (УД – С) [12];\n(УД – С) [12];\n(УД– С) [12].\nНестероидные противовоспалительные средства (применяется 1 из указанных препаратов) диклофенак натрия\nиндометацин\nдексаметазона натрия фосфат Таблетки 2-3 раза в сутки до еды (УД – С) [12];\n(УД – С) [12];\n(УД – С) [12].\nПрепараты для проведения анестезиологического пособия (применяется 1 или 2 из указанных       препаратов): проксиметакаина гидрохлорид\nлидокаина гидрохлорид\nИнстилляции в конъюнктивальную полость\nр-р в ампулах ретробульбарно (УД – С) [12];\n(УД – С) [12].\nПротивопоказания:\nтяжелое общее состояние пациента.\nДальнейшее ведение:\nПрофилактические мероприятия:\nсвоевременный плановый осмотр глазного дна у пациентов с миопией;\nпрофилактика травматизма;\nпрофилактическая периферическая лазеркоагуляция дегенераций сетчатки.\nПациента необходимо наблюдать до выздоровления на амбулаторном уровне в течение срока от 1 недели до 1 месяца, продолжить местную антибактериальную и противовоспалительную терапию от 7 дней до 1 месяца. Амбулаторное наблюдение\nокулистом по месту жительства в течение нескольких месяцев (до 1 года). Следует контролировать состояние офтальмотонуса, состояние сетчатки, наличие признаков отторжения пломбировачного материала (в случаях экстрасклеральной хирургии), и признаков эмульгации силикона (при его наличии в случае витреоретинальной хирургии), а также состояние хрусталика (если он не удален во время операции).\nИндикаторы эффективности лечения:\nповышение остроты зрения по сравнению с исходной;\nприлегание сетчатки;\nрасширение границ полей зрения;\nустранение тракции при ВМТС.\nГоспитализация\nПОКАЗАНИЯ ДЛЯ ГОСПИТАЛИЗАЦИИ С УКАЗАНИЕМ ТИПА ГОСПИТАЛИЗАЦИИ\nПоказания для плановой госпитализации:\nстарая отслойка сетчатки, занимающая нижнюю половину глазного дна и имеющая линии самоотграничения;\nретинодиализ, который представляет собой разрыв вследствие врожденных дефектов сетчатки у зубчатой линии, преимущественно в нижне-наружном квадранте глазного дна, характеризуется медленным бессимптомным течением прогрессирования отслойки сетчатки, часто с линией самоотграничения;\nотслойка сетчатки с центральным разрывом вследствие особенностей ее течения;\nретиношизис с захватом макулярной зоны или с угрозой захвата макулярной зоны;\nтракционная отслойка сетчатки;\nвитреомакулярный тракционный синдром;\nсвежая отслойка сетчатки;\nотслойка сетчатки с локализацией в верхних квадрантах;\nналичие гигантского разрыва/отрыва сетчатки от зубчатой линии (как правило, последствия травмы);\nлюбая отслойка сетчатки с разрывом любой локализации, достигшей макулы с угрозой ее отслойки;\nотслойка сетчатки с частично/полностью отслоенной макулой;\nретинальные разрывы или отрывы сетчатки с тракционным компонентом.\nПоказания для экстренной госпитализации: нет.\nИнформация\nИсточники и литература\nПротоколы заседаний Объединенной комиссии по качеству медицинских услуг МЗ РК, 2019\n1) Д. И. Антелава, Н.Н. Пивоваров, А.А.Сафоян «Первичная отслойка сетчатки Этиопатогенез, диагностика, лечение». Издательство «Сабчотасакартвело» г. Тбилиси — 1986г. 2) Астахов Ю С, Луковская Н.Г. Ретиншизис сообщение 1. Диагностика, классификация, методы обследования. // Вестник офтальмологии 2004, №1 С. 26-29. 3) Кански Джек Дж. Заболевания глазного дна. 2009 г., 2-е изд., С.268-269. 4) Duker JS, Kaiser PK, Binder S, et al. The International Vitreomacular Traction Study Group Classification of Vitreomacular Adhesion, Traction, and Macular Hole. Ophthalmology. 2013;120(12):2611–2619. 5) Ito Y, Terasaki H, Suzuki T, et al. Mapping posterior vitreous detachment by optical coherence tomography in eyes with idiopathic macular hole. Am. J. Ophthalmol. 2003;135(3):351–5. 6) Б.М. Азнабаев1, Т.Р. Мухамадеев1, А.А. Александров2, Т.И. Дибаев2 Витреомакулярный тракционный синдром по данным спектральной оптической когерентной томографии. // Медицинский вестник Башкортостан 2014. №2. С. 107-109. 7) Краснов М.М. Система хирургического лечения отслойки сетчатки // Вестн. офтальмологии. 1966.- № 1 8) Атьков О.Ю., Леонова Е.С. Планы ведения больных «Офтальмология» Доказательная медицина, ГЭОТАР –Медиа, Москва, 2011. 9) Коротких М.Э., Жданова Н.К. Титов Д.К. Анализ результатов лечения отслойки сетчатки методом экстрасклерального пломбирования // Матер.конф. ЕАКО. - Екатеринбург, 2006. 10) Крейсиг И. Минимальная хирургия отслойки сетчатки. – Москва, 2006. 11) Нероев В.В., Зуева М.В., Хорошилова-Маслова И.П., Цапенко И.В., Сарыгина О.И., Зайцева С.И., Егорова Е.Н. Закономерности морфологических и функциональных изменений сетчатки при ее отслойке и после хирургического лечения. Сообщение 1. Деконструкция и восстановление фоторецепторов // Вестн. офтальмолог. - 2008. - №1. 12) Логай И.М., Родин С.С., Драгомирецкая Е.И. и др. Использование искусственных нейронных сетей в прогнозировании возможности восстановления послеоперационной остроты зрения более 0,05 при тяжелых отслойках сетчатки // Офтальмол. журнал. - 2008. - №1. 13) Сергиенко А.Н., Столяров Г.С., Ленская О.В. Возможности восстановления зрения после операций по поводу отслойки сетчатки // Офтальмол.журнал.- 2006.-№3. 14) Степанов Ю.В., Авилова В.М. Значение диспансерного наблюдения для профилактики поздних рецидивов после операции по поводу отслойки сетчатки // Офтальмол. журнал. -2008. - №6. 15) Yasukawa T., Fukuda T., Kishimoto M., Ogura Y. Prediction of postoperative visual acuity in retinal detachment with macular involvement // Nippon GankaGakkaiZasshi. - 2005.- Vol.99(3). 16) Нероев В.В., Захарова Г.Ю., Петричева С.В. Профилактика самопроизвольной перфорации склеры при повторных хирургических операциях по поводу регматогенной отслойки сетчатки // Вестн. офтальмологии. - 2005. - №3. 17) Азнабаев М.Т., Суркова В.К., Сережин И.Н., Вавилова О.В. Преимущества и недостатки склеропластических и витреоретинальных вмешательств в хирургии отслоек сетчатки // Рефракционная хирургия и офтальмология. - 2003.- №4. 18) Волков В.В., Бржеский В.В., Ушаков Н.А. Офтальмохирургия с использованием полимеров.- Санкт-Петербург, 2003. 19) Крайссиг И. Лечение отслойки сетчатки: экстраокулярная или интраокулярная хирургия? // Тезисы докладов 2-ой Евроазиатской конференции по офтальмохирургии.- Екатеринбург, 2010.-Ч.1. 20) Ильницкий В.В. Временное и постоянное эписклеральное пломбирование в хирургии отслойки сетчатки : автореф д-ра. мед. наук:.-М.:,2005. 21) Faude F., Meier P., Wiedemann P. Scleralbucklingoperations in rhegmatousretinaldetachment // Ophthalmologe.- 2002.- Vol. 99(4).- P.308-321 22) Багдасарова Т.А., Хазен Л.З. Первые отечественные силиконовые баллон- катетеры для экстрасклеральной хирургии отслойки сетчатки // Тезисы докладов VIII Съезд офтальмологов России.- Москва, 2005. 23) Арсютов Д.Г. Использование медицинских клеев в хирургии прогрессирующей миопии и отслойки сетчатки: автореф канд. мед. наук:.-М., 2008. 24) Иванов А.Н. Лазерно-инструментальная хирургия в профилактике и лечении отслойки сетчатки (сообщение 1) // Вестн. офтальмологии.- 2002.-№4. 25) Schepens C.L., Acosta F. Scleral implants: an historical perspective // Surv. Ophthalmol.- 2002.- Vol.36(4). 26) Крейссиг И. Развитие хирургии отслойки сетчатки: как все начиналось, и что мы делаем сейчас (часть I) // РМЖ Клинич. офтальмология .- 2007.- №4. 27) Захаров В.Д., Шарипова Д.Н., Шацких А.В. Возможности лечения пролиферативной витреоретинопатии в свете современных аспектов ее этиологии и патогенеза // Офтальмохирургия. – 2006. - № 2. 28) Захаров В.Д., МазенИбрахим Хусейн Особенности витреоретинальной хирургии при отслойках сетчатки, осложненных передней пролиферативной витреоретинопатией // Офтальмохирургия. – 2007. 29) Захаров В.Д., Курцхалидзе К.Д. Лечение тяжелых отслоек сетчатки, осложненных пролиферативной витреоретинопатией // Современные технологии лечения витреоретинальной патологии: сб. тезисов VII науч. – практ. конф. – М, 2009.\nИнформация\nОРГАНИЗАЦИОННЫЕ АСПЕКТЫ ВНЕДРЕНИЯ ПРОТОКОЛА\nСписок разработчиков протокола:\nКанафьянова Эльмира Газизовна – доктор медицинских наук, главный врач ТОО «Казахский научно-исследовательский институт глазных болезней»;\nАль Асталь Мухаммед – кандидат медицинских наук, врач высшей категории, врач офтальмолог круглосуточного стационара ТОО «Казахский научно-исследовательский институт глазных болезней»;\nЖургумбаева Гульнара Кайратовна – кандидат медицинских наук, врач высшей категории, заведующая II отделением ТОО «Казахский научно-исследовательский институт глазных болезней»;\nОразбеков Лукпан Нурланович – кандидат медицинских наук, врач высшей категории, заведующая I отделением ТОО «Казахский научно-исследовательский институт глазных болезней»;\nОдинцов Константин Владимирович – врач высшей категории, врач офтальмолог круглосуточного стационара ТОО «Казахский научно-исследовательский институт глазных болезней»;\nТлеуов Кайрат – врач офтальмолог круглосуточного стационара ТОО «Казахский научно-исследовательский институт глазных болезней»;\nУрих Константин Александрович – кандидат медицинских наук, заместитель директора клиники микрохирургии глаза «Optima», Председатель филиала Казахстанского общества офтальмологов;\nЕралиева Бибихан Абдалиевна – доктор медицинских наук, заведующая кафедрой клинической фармакологии АО «Казахский медицинский университет непрерывного образования».\nКонфликт интересов: нет.\nРецензент:\nУтельбаева Зауреш Турсуновна – доктор медицинских наук, профессор кафедры офтальмологии АО «Национальный медицинский университет»\nУсловия пересмотра протокола: пересмотр протокола через 5 лет после его опубликования и с даты его вступления в действие или при наличии новых методов с уровнем доказательности.\nПрикреплённые файлы\n1. ( Отслойка_и_разрывы_сетчатки.pdf )\nОтправить файл себе на почту\nОтправить\nВнимание!\nЕсли вы не являетесь медицинским специалистом:\nЗанимаясь самолечением, вы можете нанести непоправимый вред своему здоровью.\nВыбор лекарственных средств и их дозировки, должен быть оговорен со специалистом. Только врач может назначить нужное лекарство и его дозировку с учетом заболевания и состояния организма больного.",
    "_full": "Отслойка и разрывы сетчатки\nВерсия: Клинические протоколы МЗ РК - 2019 (Казахстан)\nКатегории МКБ: Другие болезни стекловидного тела (H43.8), Другие формы отслойки сетчатки (H33.5), Отслойка сетчатки с разрывом сетчатки (H33.0), Ретинальные разрывы без отслойки сетчатки (H33.3), Ретиношизис и ретинальные кисты (H33.1), Тракционная отслойка сетчатки (H33.4)\nРазделы медицины: Офтальмология\nОбщая информация\nВерсия для печати\nСкачать или отправить файл\nКраткое описание\nОдобрен\nОбъединенной комиссией по качеству медицинских услуг\nМинистерства здравоохранения Республики Казахстан\nот «19» ноября 2019 года\nПротокол №77\nРегматогенная отслойка сетчатки – тяжелое заболевание, характеризующееся скоплением субретинальной жидкости через разрыв сетчатки между нейросенсорными слоями и подлежащим пигментным эпителием [1].\nРетиношизис и ретинальные кисты: Ретиношизис – это расслоение нейросенсорной сетчатки на внутрений и наружный листи, с повреждением нейронов и полной утратой поля зрения в области поражения [2].\nРетинальные разрывы без отслойки сетчатки - это сквозные дефекты в нейросенсорной сетчатке, которые различаются по патогенезу, конфигурации и локализации [3].\nТракционная отслойка сетчатки – происходит при натяжении (тракции), которое испытывает сетчатка со стороны стекловидного тела из-за образования в результате фибринозных тяжей или новообразованных сосудов, которые врастают в стекловидное тело [1].\nДругие формы отслойки сетчатки: Витреомакулярный тракционный синдром – хроническое состояние, связанное c неполной задней отслойкой стекловидного тела и преретинальной пролиферацией, которые вызывают тракционную деформацию макулы, механическое натяжение и повреждение макулярной сетчатки [4 - 6].\nВВОДНАЯ ЧАСТЬ\nНазвание протокола: ОТСЛОЙКА И РАЗРЫВЫ СЕТЧАТКИ\nКод(ы) МКБ-10:\nКод Название\nH33.0 Отслойка сетчатки с разрывом сетчатки\nH33.1 Ретиношизис и ретинальные кисты\nH33.3 Ретинальные разрывы без отслойки сетчатки\nH33.4 Тракционная отслойка сетчатки\nH33.5 Другие формы отслойки сетчатки\nH43.8 Витреомакулярный тракционный синдром\nДата разработки/пересмотра протокола: 2015 год (пересмотр 2019 г.)\nСокращения, используемые в протоколе:\nАЛТ – аланинтрансфераза\nАСТ – аспартаттрансфераза\nБХ – биохимический анализ\nВГД – внутриглазное давление\nВИЧ – вирус иммуннодефицита человека\nВМТС – Витреомакулярный тракционный синдром\nОАК – общий анализ крови\nОАМ – общий анализ мочи\nОС – отслойка сетчатки\nПВР – пролиферативная витреоретинопатия\nПЗ – поле зрения\nПЗР – передне-задний размер глазного яблока.\nУД – уровень доказательности\nУЗИ – ультразвуковое исследование\nЭКГ – электрокардиограмма\nЭРГ – электроретинография\nЭФИ – электрофизиологическое исследование\nПользователи протокола: врачи общей практики, врачи скорой помощи, фельдшеры, офтальмологи.\nКатегория пациентов: взрослые.\nШкала уровня доказательности:\nОценка на степень доказательности приводимых рекомендаций [1].\nУровень\nдоказательности Тип доказательности\nІ Доказательства получены в результате мета-анализа большого числа хорошо спланированных рандомизированных исследований.\nРандомизированные исследования с низким уровнем ложнопозитивных и ложнонегативных ошибок.\nІІ Доказательства основаны на результатах не менее одного хорошо спланированного рандомизированного исследования. Рандомизированные исследования с высоким уровнем ложнопозитивных и ложнонегативных ошибок.\nІІІ Доказательства основаны на результатах хорошо спланированных нерандомизированных исследований. Контролируемые исследования с одной группой больных, исследования с группой исторического контроля и т.д.\nІV Доказательства получены в результате нерандомизированных исследований. Непрямые сравнительные, описательно корелляционные исследования и исследования клинических случаев.\nV Доказательства основаны на клинических случаях и примерах\nСтепень Градация\nА Доказательство І уровня или устойчивые многочисленные данные ІІ. ІІІ или ІV уровня доказательности\nВ Доказательства ІІ. ІІІ или ІV уровня, считающиеся в целом устойчивыми данными\nС Доказательства ІІ. ІІІ или ІV уровня, но данные в целом неустойчивые\nD Слабые или несистематические эмпирические доказательства.\nКлассификация\nКлиническая классификация\nКлассификация отслойка сетчатки по Краснову М.М. [7]:\nпо механизму:\nрегматогенная (с дырчатым или клапанным разрывом сетчатки, идиопатическая);\nтракционная (травма, СД, гемофтальм);\nсмешанная (тракционно-перфоративная, перфоративно-тракционная);\nэкссудативная.\nпо виду:\nсвежая (до 1 месяца);\nнесвежая (от 1 до 3 месяцев);\nстарая (от 3 месяцев и более).\nпо распространенности:\nлокальная (занимает 1 квадрант глазного дна);\nраспространенная (занимает до 2 квадрантов глазного дна);\nсубтотальная (занимает 3 квадранта глазного дна);\nтотальная (занимает всю площадь глазного дна).\nпо высоте:\nплоская;\nвысокая;\nпузыревидная.\nпо ригидности:\nподвижная;\nполуподвижная;\nригидная.\nКлассификация отслоек сетчатки по категории тяжести:\nI категория: cетчатка полностью мобильна, расправляемость хорошая, тракционный компонент со стороны стекловидного тела выражено слабо. После 3-4 дней постельного режима сетчатка прилежит в области разрыва к сосудистой оболочке. Фиксированные складки сетчатки и шварты в стекловидном теле отсутствуют.\nII категория: характеризуется тракцией со стороны стекловидного тела, после 3-4 дней постельного режима сетчатка частично (прилежит) расправляется, но полностью на месте разрыва не прилегает. Отмечаются шварты стекловидного тела, соединенные с клапаном разрыва, а также отслойка его стекловидной пластинки. Фиксированные складки сетчатки отсутствуют.\nIII категория: имеются выраженные тракционные изменения со стороны стекловидного тела. Нет тенденции к расправлению сетчатки даже после длительного постельного режима. Грубые фиксированные складки малоподвижны при движении глаза.\nКлассификация отслоек сетчатки с ПВР [1]:\nСтадия ПВР А. – стекловидное тело мутное, с пигментными глыбками. Пигментные глыбки на поверхности отслоенной сетчатки и в нижних отделах витреальной полости.\nСтадия ПВР В. – сморщивание поверхности отслоенной сетчатки, уменьшение ее подвижности, ретинальные сосуды извиты, край разрыва сетчатки завернут, стекловидное тело становится малоподвижным.\nСтадия ПВР С posterior – кзади от экватора формируются фокальные, диффузные фиксированные складки сетчатки, наличие субретинальных тяжей.\nСтадия ПВР Canterior – кпереди от экватора формируются фиксированные складки сетчатки, переднее смещение периферической сетчатки, плотное, тяжистое стекловидное тело.\nКлассификация ретиношизиса и ретинальные кисты по Астахову Ю.С., Луковской Н.Г. [2]:\nПо локализации разрыва в сетчатке:\nво внутреннем листке;\nв наружном листке;\nв обоих листках;\nбез разрывов.\nПо течению:\nстационарное с рубцеванием сетчатки;\nпрогрессирующее без демаркации с неровными границами;\nосложненное:\n- кровоизлияние в стекловидное тело;\n- кровоизлияние в полость кисты;\n- с переходом в отслойку сетчатки.\nПо виду:\nпервичный;\nвторичный;\nПо этиопатогенезу:\nнаследственный:\n- юношеский, сцепленный с Х-хромосомой;\n- при синдроме Вагнера;\n- при синдроме Гольдмана-Фавра.\nприобретенный:\nДегенеративный (сенильный):\n- из типичной кистозной периферической дегенерации;\n- из ретикулярной кистозной периферической дегенерации.\nМиопический:\n- из типичной кистозной периферической дегенерации;\n- из ретикулярной кистозной периферической дегенерации\n· после травмы\n· после тромбоза центральной вены сетчатки\n· после операции по поводу отслойки сетчатки\n· при диабете\n· при увеите\nПо локализации:\nцентральная;\nпериферическая;\nкомбинированная.\nПо форме:\nплоская;\nбуллезная.\nПо стороне поражения:\nодносторонний;\nдвусторонний.\nКлассификация ретинальных разрывов без отслойки сетчатки [3]:\nПо патогенезу:\nклапанные разрыв возникают при динамичекой витреоретинальной тракции. Наиболее часто встречается в верхнем квадранте (чаще височном).\nдырчатые разрывы возникают как следствие хронической атрофии сетчатки и бывают овальными и круглыми.\nПо конфигурации\nU-разрывы, клапанные или подковообразные разрывы, вершина которой тянется в стекловидное тело, а основание (расположенно ближе кпереди) остается прикрепленным к остальной сетчатке.\nНеполный  U- образный или L- образный разрыв.\nРазрыв с крышечкой, когда участок сетчатки полностью оторван отслоенным стекловидным телом.\nОтрыв (диализ) – это циркулярный разрыв вдоль зубчатой линии с прикрепленным по задней поверхности разрыва стекловидным телом.\nГигантские разрывы, распространяющие более чем на 90° окружности глазного яблока. Это вариант U –разрыва с прикреплением стекловидного тела по переднему краю разрыва.\nКлассификация витреомакулярного тракционного  синдрома[4-6].\nВиды Описание по OКT картине Дополнительные признаки Симптомы Соответствует стадии макулярного отверстия:\nВитреомакулярная адгезия По крайней мере должен присуствовать один из следующих изменений на ОКТ картине:\n(I) Частичное отслоение стекловидного тела, указывающий на подъем кортикального слоя стекловидного тела над поверхностью сетчатки в перифовеалярной области.\n(II) Постоянное прикрепление стекловидного тела к макуле в пределах 3 мм в радиус от центра фовеа.\n(III) острый угол между задним гиалоидом и внутренней поверхностью сетчатки\n(IV) отсутствие изменений фовеального контура или морфологии сетчатки нет нет 0 стадия\nВитреомакулярная тракция По крайней мере должен присуствовать один из следующих изменений на ОКТ картине:\n(I) Частичное отслоение стекловидного тела, указывающий на подъем кортикального слоя стекловидного тела над поверхностью сетчатки в перифовеалярной области.\n(II) Постоянное прикрепление стекловидного тела к макуле в пределах 3 мм в радиус от центра фовеа.\n(III) острый угол между задним гиалоидом и внутренней поверхность сетчатки.\n(IV) отсутствие изменений фовеального контура или морфологии сетчатки (искривление фовеальной поверхности, интраретинальные структурные изменения как формирование псевдокисты, подъем фовеа от ПЭ, или комбинация любого из этих трех признаков).\n(v) Отсутствие нарушение непрерывности по всей толщине сетчатки   Фовеалярная псевдокиста, утолщение макулы, увеличение проницаемости капилляров сетчатки, макулярный шизис, кистозный макулярный отек,\nотслоение сетчатки Снижение или искажение  зрения  1 Стадия (надвигающийся макулярный разрыв) 2 стадия (витриомакулярная тракция с полным малым и средним макулярным разрывом) или\n3 стадия\n(витриомакулярная тракция с полным средним и большим макулярным разрывом)\nВиды OКT- классификация\nВитреомакулярная адгезия (I) Фокальная: ширина крепления ≤1500 мкм\n(II) Широкая: ширина крепления> 1500 мкм\n(I) Одновременная: связанный с другими изменениями в макулярной зоне (например, возрастная макулярная дегенерация, окклюзия центральной вены сетчатки, диабетический макулярный отек)\n(II) Изолированная: не связан с другими нарушениями макулярной зоны\nВитреомулярная тракция\nФокальная: ширина крепления ≤1500 мкм\n(II) Широкая: ширина крепления> 1500 мкм\n(I) Одновременная: связанный с другими изменениями в макулярной зоне (например, возрастная макулярная дегенерация, окклюзия центральной вены сетчатки, диабетический макулярный отек)\n(II) Изолированная: не связан с другими нарушениями макулярной зоны\nДиагностика\nМЕТОДЫ, ПОДХОДЫ И ПРОЦЕДУРЫ ДИАГНОСТИКИ\nДиагностические критерии [1,9 - 11]\nЖалобы:\nснижение остроты зрения;\nпоявление дефекта в периферическом поле зрения в виде темной завесы;\nискажение зрения.\nАнамнез:\nанте/постнатальный анамнез;\nсведения о сопутствующих и ранее перенесенных заболеваниях (включая аллергоанамнез);\nтравмы органа зрения.\nФизикальное обследование: нет.\nЛабораторные исследования: нет.\nИнструментальные исследования:\nопределение остроты зрения без/с очковой коррекцией – отсутствие/снижение остроты зрения;\nизмерение внутриглазного давления – повышение/снижение ВГД;\nВ-скан глаз (эхобиометрия): наличие ОС, ее высота, распространенность и конфигурация;\nА-скан глаз (эхобиометрия): патологические эхосигналы, наличие/отсутствие увеличения ПЗР;\nэлектрофизиологическое исследование зрительного нерва и сетчатки ‒ снижение проводимости зрительного нерва, снижение активности наружных слоев сетчатки;\nисследование полей зрения ‒ участки выпадения, соответствующие противоположенной локализации ОС.\nоптическая когерентная томография – наличие трации в макулярной зоны, эпиретниальная мембрана, макулярный разрыв.\nПоказания для консультации специалистов:\nконсультация невропатолога при наличии неврологической патологии;\nконсультация ЛОР врача для исключения острой инфекции;\nконсультация стоматолога для исключения острой инфекции;\nконсультация терапевта для исключения противопоказаний со стороны общего состояния.\nДифференциальный диагноз\nДифференциальная диагностика первичной отслойки сетчатки cо вторичной отслойкой сетчатки и отслойки сосудистой оболочки\nДиагноз Обоснование для дифференциальной диагностики Обследования Критерии исключения диагноза\nВторичная отслойка сетчатки\nНаличие проминенции сетчатки вследствие наличия патологического образования позади нее; преимущественно односторонний характер;\nчасто боковое смещение глазного яблока;\nнарушение репозиции глазного яблока при надавливании на глаз через сомкнутые веки;\nизменение рефракции вследствие изменения длины аксиальной оси глазного яблока и радиуса кривизны роговицы;\nв развитии процесса играют роль травма, гриппозная инфекция, воспалительные заболевания в придаточных пазухах носа;\nкартина хронического неспецифического воспаления, боли в орбите, отек век, хемоз, ограничение движения глазного яблока, диплопия, нередко повышение внутриглазного давления, экзофтальм;\nчасто картина застойного диска зрительного нерва при вовлечении заднего отдела орбиты.\nВизометрия: безболезненное или резкое снижение зрения (при захвате маклярной зоны)\nПериметрия: Выпадение в поле зрения возникает на стороне, противоположной расположению отслойки. «пелена» или «шторка» перед глазом\nОфтальмоскопия: отслойка сетчатки с соединительнотканными тяжами (шварт) или преретинальными мембранами, скоплениями экссудата, растяжением ее растущей опухолью или новообразованными сосудами, гематомой.\nУЗИ: отслойка сетчатки, цилиохориоидальная отслойка, кровоизлияние в стекловидное тело, хориоидальная меланома и шварты 1.Наличие разрыва сетчатки, и тракции со стороны стекловидного тела.\n2.отсутствие различных заболеваний и патологических состояний глаза\nОтслойка сосудистой оболочки\nвстречается как осложнение при хирургии глаукомы;\nотличия при офтальмоскопии: отсутствие разрывов сетчатки, отсутствие пространства и жидкости между сетчаткой и сосудистой\nоболочкой, отслоенного пузыря цвет темно – серый. Визометрия: снижение зрения\nПериметрия: относительная скатома.\nОфтальмоскопия: очаг шаровидной формы и занимает один или два квадранта, обычно кпереди от экватора. Она легко просвечивается, цвет ее светлый, проходящие по ней сосуды ярко-розового цвета.  1.Наличие разрыва сетчатки, и тракции со стороны стекловидного тела.\n2. наличие абсолютной скотомы\nЛечение (амбулатория)\nТАКТИКА ЛЕЧЕНИЯ НА АМБУЛАТОРНОМ УРОВНЕ: нет.\nЛечение (стационар)\nТАКТИКА ЛЕЧЕНИЯ НА СТАЦИОНАРНОМ УРОВНЕ\nКарта наблюдения пациента, маршрутизация пациента (схемы):\nЦели лечения:\nанатомическое прилегание сетчатки;\nустранение тракции;\nповышение зрительных функций.\nТактика лечения: лечение только хирургическое. До операции назначаются местно мидриатики, противовоспалительные и антибактериальные препараты. Метод хирургического вмешательства определяется хирургом во время осмотра. Во время операции также применяются местные антибактериальные, противовоспалительные препараты и анестетики в виде капель и ретробульбарных инъекций. В послеоперационном периоде назначаются местно антибактериальные, противовоспалительные препараты. При выписке пациенту даются подробные рекомендации с применением глазных капель самостоятельно.\nНемедикаментозное лечение:\n·режим I, II;\n·стол №15.\nМедикаментозное лечение:\nФармакотерапевтическая группа Международное непатентованное наименование ЛС Способ применения Уровень доказательности\nМидриатики короткого и длительного действия(применяется 1/2 из указанных препаратов):\nтропикамид\nфенилэфрина гидрохлорид +\nТропикамид\nатропин\nИнстиляции в конъюнктивальную полость (УД – С) [12];\n(УД – В) [12];\n(УД – С) [12].\nАнтибактериальные глазные капли(применяется 1 из указанных препаратов) тобрамицин\nлевофлоксацин\nципрофлоксацин\nмоксифлоксацин В конъюнктивальный мешок\n(УД – С) [12];\n(УД – С) [12];\n(УД – С)[12];\n(УД – С)\nПротивовоспалительные глазные капли (применяется 1 из указанных препаратов) дексаметазон\nнепафенак\nдиклофенак натрия Инстилляции в конъюнктивальную полость\nсуспензия по 1 капле 3 раза в день (УД – С)[12];\n(УД – С) [12];\n(УД – С) [12].\nКомбинированные препараты (применяется 1 из указанных препаратов) тобрамицин + дексаметазон\nгентамицин + дексаметазон в\nмоксифлоксацин+дексаметазон в конъюнктивальный мешок (УД – С) [12];\n(УД – С) [12];\n(УД– С) [12].\nНестероидные противовоспалительные средства (применяется 1 из указанных препаратов) диклофенак натрия\nиндометацин\nдексаметазона натрия фосфат Таблетки 2-3 раза в сутки до еды (УД – С) [12];\n(УД – С) [12];\n(УД – С) [12].\nПрепараты для проведения анестезиологического пособия (применяется 1 или 2 из указанных       препаратов): проксиметакаина гидрохлорид\nлидокаина гидрохлорид\nИнстилляции в конъюнктивальную полость\nр-р в ампулах ретробульбарно (УД – С) [12];\n(УД – С) [12].\nПротивопоказания:\nтяжелое общее состояние пациента.\nДальнейшее ведение:\nПрофилактические мероприятия:\nсвоевременный плановый осмотр глазного дна у пациентов с миопией;\nпрофилактика травматизма;\nпрофилактическая периферическая лазеркоагуляция дегенераций сетчатки.\nПациента необходимо наблюдать до выздоровления на амбулаторном уровне в течение срока от 1 недели до 1 месяца, продолжить местную антибактериальную и противовоспалительную терапию от 7 дней до 1 месяца. Амбулаторное наблюдение\nокулистом по месту жительства в течение нескольких месяцев (до 1 года). Следует контролировать состояние офтальмотонуса, состояние сетчатки, наличие признаков отторжения пломбировачного материала (в случаях экстрасклеральной хирургии), и признаков эмульгации силикона (при его наличии в случае витреоретинальной хирургии), а также состояние хрусталика (если он не удален во время операции).\nИндикаторы эффективности лечения:\nповышение остроты зрения по сравнению с исходной;\nприлегание сетчатки;\nрасширение границ полей зрения;\nустранение тракции при ВМТС.\nГоспитализация\nПОКАЗАНИЯ ДЛЯ ГОСПИТАЛИЗАЦИИ С УКАЗАНИЕМ ТИПА ГОСПИТАЛИЗАЦИИ\nПоказания для плановой госпитализации:\nстарая отслойка сетчатки, занимающая нижнюю половину глазного дна и имеющая линии самоотграничения;\nретинодиализ, который представляет собой разрыв вследствие врожденных дефектов сетчатки у зубчатой линии, преимущественно в нижне-наружном квадранте глазного дна, характеризуется медленным бессимптомным течением прогрессирования отслойки сетчатки, часто с линией самоотграничения;\nотслойка сетчатки с центральным разрывом вследствие особенностей ее течения;\nретиношизис с захватом макулярной зоны или с угрозой захвата макулярной зоны;\nтракционная отслойка сетчатки;\nвитреомакулярный тракционный синдром;\nсвежая отслойка сетчатки;\nотслойка сетчатки с локализацией в верхних квадрантах;\nналичие гигантского разрыва/отрыва сетчатки от зубчатой линии (как правило, последствия травмы);\nлюбая отслойка сетчатки с разрывом любой локализации, достигшей макулы с угрозой ее отслойки;\nотслойка сетчатки с частично/полностью отслоенной макулой;\nретинальные разрывы или отрывы сетчатки с тракционным компонентом.\nПоказания для экстренной госпитализации: нет.\nИнформация\nИсточники и литература\nПротоколы заседаний Объединенной комиссии по качеству медицинских услуг МЗ РК, 2019\n1) Д. И. Антелава, Н.Н. Пивоваров, А.А.Сафоян «Первичная отслойка сетчатки Этиопатогенез, диагностика, лечение». Издательство «Сабчотасакартвело» г. Тбилиси — 1986г. 2) Астахов Ю С, Луковская Н.Г. Ретиншизис сообщение 1. Диагностика, классификация, методы обследования. // Вестник офтальмологии 2004, №1 С. 26-29. 3) Кански Джек Дж. Заболевания глазного дна. 2009 г., 2-е изд., С.268-269. 4) Duker JS, Kaiser PK, Binder S, et al. The International Vitreomacular Traction Study Group Classification of Vitreomacular Adhesion, Traction, and Macular Hole. Ophthalmology. 2013;120(12):2611–2619. 5) Ito Y, Terasaki H, Suzuki T, et al. Mapping posterior vitreous detachment by optical coherence tomography in eyes with idiopathic macular hole. Am. J. Ophthalmol. 2003;135(3):351–5. 6) Б.М. Азнабаев1, Т.Р. Мухамадеев1, А.А. Александров2, Т.И. Дибаев2 Витреомакулярный тракционный синдром по данным спектральной оптической когерентной томографии. // Медицинский вестник Башкортостан 2014. №2. С. 107-109. 7) Краснов М.М. Система хирургического лечения отслойки сетчатки // Вестн. офтальмологии. 1966.- № 1 8) Атьков О.Ю., Леонова Е.С. Планы ведения больных «Офтальмология» Доказательная медицина, ГЭОТАР –Медиа, Москва, 2011. 9) Коротких М.Э., Жданова Н.К. Титов Д.К. Анализ результатов лечения отслойки сетчатки методом экстрасклерального пломбирования // Матер.конф. ЕАКО. - Екатеринбург, 2006. 10) Крейсиг И. Минимальная хирургия отслойки сетчатки. – Москва, 2006. 11) Нероев В.В., Зуева М.В., Хорошилова-Маслова И.П., Цапенко И.В., Сарыгина О.И., Зайцева С.И., Егорова Е.Н. Закономерности морфологических и функциональных изменений сетчатки при ее отслойке и после хирургического лечения. Сообщение 1. Деконструкция и восстановление фоторецепторов // Вестн. офтальмолог. - 2008. - №1. 12) Логай И.М., Родин С.С., Драгомирецкая Е.И. и др. Использование искусственных нейронных сетей в прогнозировании возможности восстановления послеоперационной остроты зрения более 0,05 при тяжелых отслойках сетчатки // Офтальмол. журнал. - 2008. - №1. 13) Сергиенко А.Н., Столяров Г.С., Ленская О.В. Возможности восстановления зрения после операций по поводу отслойки сетчатки // Офтальмол.журнал.- 2006.-№3. 14) Степанов Ю.В., Авилова В.М. Значение диспансерного наблюдения для профилактики поздних рецидивов после операции по поводу отслойки сетчатки // Офтальмол. журнал. -2008. - №6. 15) Yasukawa T., Fukuda T., Kishimoto M., Ogura Y. Prediction of postoperative visual acuity in retinal detachment with macular involvement // Nippon GankaGakkaiZasshi. - 2005.- Vol.99(3). 16) Нероев В.В., Захарова Г.Ю., Петричева С.В. Профилактика самопроизвольной перфорации склеры при повторных хирургических операциях по поводу регматогенной отслойки сетчатки // Вестн. офтальмологии. - 2005. - №3. 17) Азнабаев М.Т., Суркова В.К., Сережин И.Н., Вавилова О.В. Преимущества и недостатки склеропластических и витреоретинальных вмешательств в хирургии отслоек сетчатки // Рефракционная хирургия и офтальмология. - 2003.- №4. 18) Волков В.В., Бржеский В.В., Ушаков Н.А. Офтальмохирургия с использованием полимеров.- Санкт-Петербург, 2003. 19) Крайссиг И. Лечение отслойки сетчатки: экстраокулярная или интраокулярная хирургия? // Тезисы докладов 2-ой Евроазиатской конференции по офтальмохирургии.- Екатеринбург, 2010.-Ч.1. 20) Ильницкий В.В. Временное и постоянное эписклеральное пломбирование в хирургии отслойки сетчатки : автореф д-ра. мед. наук:.-М.:,2005. 21) Faude F., Meier P., Wiedemann P. Scleralbucklingoperations in rhegmatousretinaldetachment // Ophthalmologe.- 2002.- Vol. 99(4).- P.308-321 22) Багдасарова Т.А., Хазен Л.З. Первые отечественные силиконовые баллон- катетеры для экстрасклеральной хирургии отслойки сетчатки // Тезисы докладов VIII Съезд офтальмологов России.- Москва, 2005. 23) Арсютов Д.Г. Использование медицинских клеев в хирургии прогрессирующей миопии и отслойки сетчатки: автореф канд. мед. наук:.-М., 2008. 24) Иванов А.Н. Лазерно-инструментальная хирургия в профилактике и лечении отслойки сетчатки (сообщение 1) // Вестн. офтальмологии.- 2002.-№4. 25) Schepens C.L., Acosta F. Scleral implants: an historical perspective // Surv. Ophthalmol.- 2002.- Vol.36(4). 26) Крейссиг И. Развитие хирургии отслойки сетчатки: как все начиналось, и что мы делаем сейчас (часть I) // РМЖ Клинич. офтальмология .- 2007.- №4. 27) Захаров В.Д., Шарипова Д.Н., Шацких А.В. Возможности лечения пролиферативной витреоретинопатии в свете современных аспектов ее этиологии и патогенеза // Офтальмохирургия. – 2006. - № 2. 28) Захаров В.Д., МазенИбрахим Хусейн Особенности витреоретинальной хирургии при отслойках сетчатки, осложненных передней пролиферативной витреоретинопатией // Офтальмохирургия. – 2007. 29) Захаров В.Д., Курцхалидзе К.Д. Лечение тяжелых отслоек сетчатки, осложненных пролиферативной витреоретинопатией // Современные технологии лечения витреоретинальной патологии: сб. тезисов VII науч. – практ. конф. – М, 2009.\nИнформация\nОРГАНИЗАЦИОННЫЕ АСПЕКТЫ ВНЕДРЕНИЯ ПРОТОКОЛА\nСписок разработчиков протокола:\nКанафьянова Эльмира Газизовна – доктор медицинских наук, главный врач ТОО «Казахский научно-исследовательский институт глазных болезней»;\nАль Асталь Мухаммед – кандидат медицинских наук, врач высшей категории, врач офтальмолог круглосуточного стационара ТОО «Казахский научно-исследовательский институт глазных болезней»;\nЖургумбаева Гульнара Кайратовна – кандидат медицинских наук, врач высшей категории, заведующая II отделением ТОО «Казахский научно-исследовательский институт глазных болезней»;\nОразбеков Лукпан Нурланович – кандидат медицинских наук, врач высшей категории, заведующая I отделением ТОО «Казахский научно-исследовательский институт глазных болезней»;\nОдинцов Константин Владимирович – врач высшей категории, врач офтальмолог круглосуточного стационара ТОО «Казахский научно-исследовательский институт глазных болезней»;\nТлеуов Кайрат – врач офтальмолог круглосуточного стационара ТОО «Казахский научно-исследовательский институт глазных болезней»;\nУрих Константин Александрович – кандидат медицинских наук, заместитель директора клиники микрохирургии глаза «Optima», Председатель филиала Казахстанского общества офтальмологов;\nЕралиева Бибихан Абдалиевна – доктор медицинских наук, заведующая кафедрой клинической фармакологии АО «Казахский медицинский университет непрерывного образования».\nКонфликт интересов: нет.\nРецензент:\nУтельбаева Зауреш Турсуновна – доктор медицинских наук, профессор кафедры офтальмологии АО «Национальный медицинский университет»\nУсловия пересмотра протокола: пересмотр протокола через 5 лет после его опубликования и с даты его вступления в действие или при наличии новых методов с уровнем доказательности.\nПрикреплённые файлы\n1. ( Отслойка_и_разрывы_сетчатки.pdf )\nОтправить файл себе на почту\nОтправить\nВнимание!\nЕсли вы не являетесь медицинским специалистом:\nЗанимаясь самолечением, вы можете нанести непоправимый вред своему здоровью.\nВыбор лекарственных средств и их дозировки, должен быть оговорен со специалистом. Только врач может назначить нужное лекарство и его дозировку с учетом заболевания и состояния организма больного."
  }
}